sausagelink
