Metadata-Version: 2.1
Name: sausagelink
Version: 1.5.3
Summary: Like Blockchain But Tastier™️
Home-page: https://github.com/maxhumber/sausagelink
Author: Max Humber
Author-email: max.humber@gmail.com
License: MIT
Keywords: blockchain,ledger,sha256
Platform: UNKNOWN
Classifier: Development Status :: 5 - Production/Stable
Classifier: Intended Audience :: Developers
Classifier: License :: OSI Approved :: MIT License
Classifier: Natural Language :: English
Classifier: Programming Language :: Python :: 3
Classifier: Programming Language :: Python :: 3.6
Classifier: Programming Language :: Python :: 3.7
Classifier: Topic :: Security :: Cryptography
Requires-Python: >=3.6
